{
  "name": "Comment",
  "base": "PersistedModel",
  "idInjection": false,
  "options": {
    "validateUpsert": true
  },
  "mysql": {
    "schema": "brainfock_node",
    "table": "v_comment"
  },
  "scope": {
    "include": "user"
  },
  "properties": {
    "id": {
      "type": "Number",
      "id": true,
      "generated": true,
      "length": null,
      "precision": 10,
      "scale": 0,
      "mysql": {
        "columnName": "id",
        "dataType": "int",
        "dataLength": null,
        "dataPrecision": 10,
        "dataScale": 0,
        "nullable": "N"
      },
      "_selectable": false
    },
    "parentId": {
      "type": "Number",
      "required": false,
      "length": null,
      "precision": 10,
      "scale": 0,
      "mysql": {
        "columnName": "parent_id",
        "dataType": "int",
        "dataLength": null,
        "dataPrecision": 10,
        "dataScale": 0,
        "nullable": "Y"
      },
      "_selectable": true
    },
    "threadId": {
      "type": "Number",
      "required": false,
      "length": null,
      "precision": 10,
      "scale": 0,
      "mysql": {
        "columnName": "thread_id",
        "dataType": "int",
        "dataLength": null,
        "dataPrecision": 10,
        "dataScale": 0,
        "nullable": "Y"
      },
      "_selectable": true
    },
    "entityId": {
      "type": "Number",
      "required": false,
      "length": null,
      "precision": 10,
      "scale": 0,
      "mysql": {
        "columnName": "entity_id",
        "dataType": "int",
        "dataLength": null,
        "dataPrecision": 10,
        "dataScale": 0,
        "nullable": "Y"
      },
      "_selectable": true
    },
    "authorId": {
      "type": "Number",
      "required": false,
      "length": null,
      "precision": 10,
      "scale": 0,
      "mysql": {
        "columnName": "author_id",
        "dataType": "int",
        "dataLength": null,
        "dataPrecision": 10,
        "dataScale": 0,
        "nullable": "Y"
      },
      "_selectable": true
    },
    "authorIp": {
      "type": "String",
      "required": true,
      "length": 250,
      "precision": null,
      "scale": null,
      "mysql": {
        "columnName": "authorIp",
        "dataType": "varchar",
        "dataLength": 250,
        "dataPrecision": null,
        "dataScale": null,
        "nullable": "N"
      },
      "_selectable": false
    },
    "text": {
      "type": "String",
      "required": true,
      "length": 65535,
      "precision": null,
      "scale": null,
      "mysql": {
        "columnName": "text",
        "dataType": "text",
        "dataLength": 65535,
        "dataPrecision": null,
        "dataScale": null,
        "nullable": "Y"
      },
      "_selectable": true
    },
    "textHash": {
      "type": "String",
      "required": false,
      "length": 32,
      "precision": null,
      "scale": null,
      "mysql": {
        "columnName": "text_hash",
        "dataType": "varchar",
        "dataLength": 32,
        "dataPrecision": null,
        "dataScale": null,
        "nullable": "N"
      },
      "_selectable": false
    },
    "createdOn": {
      "type": "Date",
      "required": true,
      "length": null,
      "precision": null,
      "scale": null,
      "mysql": {
        "columnName": "created_on",
        "dataType": "datetime",
        "dataLength": null,
        "dataPrecision": null,
        "dataScale": null,
        "nullable": "N"
      },
      "_selectable": false
    },
    "deleted": {
      "type": "Number",
      "required": true,
      "length": null,
      "precision": 3,
      "scale": 0,
      "mysql": {
        "columnName": "deleted",
        "dataType": "tinyint",
        "dataLength": null,
        "dataPrecision": 3,
        "dataScale": 0,
        "nullable": "N"
      },
      "_selectable": false
    },
    "status": {
      "type": "String",
      "required": false,
      "length": 8,
      "precision": null,
      "scale": null,
      "mysql": {
        "columnName": "status",
        "dataType": "enum",
        "dataLength": 8,
        "dataPrecision": null,
        "dataScale": null,
        "nullable": "Y"
      },
      "_selectable": true
    },
    "rating": {
      "type": "Number",
      "required": false,
      "length": null,
      "precision": 12,
      "scale": null,
      "mysql": {
        "columnName": "rating",
        "dataType": "float",
        "dataLength": null,
        "dataPrecision": 12,
        "dataScale": null,
        "nullable": "N"
      },
      "_selectable": false
    },
    "countPositiveVotes": {
      "type": "Number",
      "required": false,
      "length": null,
      "precision": 10,
      "scale": 0,
      "mysql": {
        "columnName": "count_positive_votes",
        "dataType": "int",
        "dataLength": null,
        "dataPrecision": 10,
        "dataScale": 0,
        "nullable": "N"
      },
      "_selectable": false
    },
    "countNegativeVotes": {
      "type": "Number",
      "required": false,
      "length": null,
      "precision": 10,
      "scale": 0,
      "mysql": {
        "columnName": "count_negative_votes",
        "dataType": "int",
        "dataLength": null,
        "dataPrecision": 10,
        "dataScale": 0,
        "nullable": "Y"
      },
      "_selectable": true
    },
    "notifyMe": {
      "type": "Number",
      "required": false,
      "length": null,
      "precision": 3,
      "scale": 0,
      "mysql": {
        "columnName": "notify_me",
        "dataType": "tinyint",
        "dataLength": null,
        "dataPrecision": 3,
        "dataScale": 0,
        "nullable": "Y"
      },
      "_selectable": true
    },
    "level": {
      "type": "Number",
      "required": false,
      "length": null,
      "precision": 5,
      "scale": 0,
      "mysql": {
        "columnName": "level",
        "dataType": "smallint",
        "dataLength": null,
        "dataPrecision": 5,
        "dataScale": 0,
        "nullable": "Y"
      },
      "_selectable": true
    },
    "ownerUserId": {
      "type": "Number",
      "required": false,
      "length": null,
      "precision": 10,
      "scale": 0,
      "mysql": {
        "columnName": "owner_user_id",
        "dataType": "int",
        "dataLength": null,
        "dataPrecision": 10,
        "dataScale": 0,
        "nullable": "Y"
      },
      "_selectable": true
    },
    "accessPrivateYn": {
      "type": "Number",
      "required": false,
      "length": null,
      "precision": 3,
      "scale": 0,
      "mysql": {
        "columnName": "access_private_yn",
        "dataType": "tinyint",
        "dataLength": null,
        "dataPrecision": 3,
        "dataScale": 0,
        "nullable": "Y"
      },
      "_selectable": true
    }
  },
  "validations": [],
  "relations": {
    "user": {
      "type": "belongsTo",
      "model": "User",
      "foreignKey": "authorId"
    }
  },
  "acls": [
    {
      "accessType": "*",
      "principalType": "ROLE",
      "principalId": "$everyone",
      "permission": "DENY"
    },
    {
      "accessType": "EXECUTE",
      "principalType": "ROLE",
      "principalId": "commentEntityAccess",
      "permission": "ALLOW",
      "property": "find"
    },
    {
      "accessType": "EXECUTE",
      "principalType": "ROLE",
      "principalId": "commentEntityAccess",
      "permission": "ALLOW",
      "property": "findById"
    }
  ],
  "methods": {}
}
